Metadata-Version: 2.1
Name: federated-learning
Version: 1.0
Summary: Federated learning library
Home-page: UNKNOWN
Author: M Ahmed Hassan
Author-email: mrmahmed15@gmail.com
License: https://github.com/mrmahmed/federetad_learning
Platform: UNKNOWN
